{
"title": "Face Wash - Neem Tulsi",
"description": "The natural base maintains balance of the skin. Its regular use gives spotless skin with glowing complexion.",
"images": [
	"assets/photo/FaceWash1.jpg",
	"assets/photo/FaceWash2.jpg"
],
"advantages": ["(-) The natural base maintains oil balance of the skin <br>",
"(-) Regular use gives spotless and glowing complexion <br>",
"(-) This special face wash enriched with disinfectants and purifiers <br>",
"(-) Neem and Tulsi cleans the acne prone oily skin thoroughly without any irritation  <br>",
"(-) Glycerin prevent skin from drying" ],
"how-to-use" : [
	"(-) Wash your face with plain water. " ,
	"(-) Apply Face wash and gently rub with fingers. ",
	"(-) Wash the face thoroughly with plain water."],
"available": "<br>120 ml at MRP ₹ 140",
"prev": "hair_shampoo",
"next": "nourishing_cream"
}
